{"importBase":"import","nativeBase":"native","name":"main","deps":[],"uuids":["129nQ9DsBLAZoyEjHOOmfN","20g1ukYUVPvKWKBRznAKo+","2cFNJ/D29J5JKr8SuI0+e5","51W0YXGh9GvaXhV08JurMh","54TknWPwVPqJqeCR+Y/Czo","57UgcWSMhKGYrPQcn4d3+w","5cCnoYzVdF15ygww0+BE8m","61T1JT9ZFDRYVB0ywpUsIW","68wtFPvmpOuLfp8MiOa1tx","6f01cf7f-81bf-4a7e-bd5d-0afc19696480@b47c0@40c10","6f01cf7f-81bf-4a7e-bd5d-0afc19696480@b47c0@74afd","6f01cf7f-81bf-4a7e-bd5d-0afc19696480@b47c0@7d38f","6f01cf7f-81bf-4a7e-bd5d-0afc19696480@b47c0@8fd34","6f01cf7f-81bf-4a7e-bd5d-0afc19696480@b47c0@bb97f","6f01cf7f-81bf-4a7e-bd5d-0afc19696480@b47c0@e9a6d","92kXguVhlFPJV+SLm9H8uv","95EkngnxZFbYuFpsqVTaFr","aaCa2pRcZECqJPeDrtQXbR","d032ac98-05e1-4090-88bb-eb640dcb5fc1@b47c0@40c10","d032ac98-05e1-4090-88bb-eb640dcb5fc1@b47c0@74afd","d032ac98-05e1-4090-88bb-eb640dcb5fc1@b47c0@7d38f","d032ac98-05e1-4090-88bb-eb640dcb5fc1@b47c0@8fd34","d032ac98-05e1-4090-88bb-eb640dcb5fc1@b47c0@bb97f","d032ac98-05e1-4090-88bb-eb640dcb5fc1@b47c0@e9a6d","e63ydYhNpA4rqi9oDhHc67","e9k4GpMbFEz71hEnlW9EG/","f80KUJRIBIOLDKiyPGqX0D","fdjsU2o1RKF5x0TziDw3jI","fepexl1EBJjq0Zbvi5flCD","040y0TEi5KJYwGi5Sgh2SH","0abd670aa","0d0a955ce","0f2e19270","129nQ9DsBLAZoyEjHOOmfN@6c48a","129nQ9DsBLAZoyEjHOOmfN@f9941","20g1ukYUVPvKWKBRznAKo+@6c48a","20g1ukYUVPvKWKBRznAKo+@f9941","2cFNJ/D29J5JKr8SuI0+e5@6c48a","2cFNJ/D29J5JKr8SuI0+e5@f9941","51W0YXGh9GvaXhV08JurMh@6c48a","51W0YXGh9GvaXhV08JurMh@f9941","54TknWPwVPqJqeCR+Y/Czo@6c48a","54TknWPwVPqJqeCR+Y/Czo@f9941","57UgcWSMhKGYrPQcn4d3+w@6c48a","57UgcWSMhKGYrPQcn4d3+w@f9941","61T1JT9ZFDRYVB0ywpUsIW@6c48a","61T1JT9ZFDRYVB0ywpUsIW@f9941","64MZ1jOO5IbaYZXR02t8td","67ZT/BRJVG7YjQ0Bm0PIaY","68wtFPvmpOuLfp8MiOa1tx@6c48a","68wtFPvmpOuLfp8MiOa1tx@f9941","6fAc9/gb9Kfr1dCvwZaWSA@b47c0","92kXguVhlFPJV+SLm9H8uv@6c48a","92kXguVhlFPJV+SLm9H8uv@f9941","95EkngnxZFbYuFpsqVTaFr@6c48a","95EkngnxZFbYuFpsqVTaFr@f9941","aaCa2pRcZECqJPeDrtQXbR@6c48a","aaCa2pRcZECqJPeDrtQXbR@f9941","d0MqyYBeFAkIi762QNy1/B@b47c0","e63ydYhNpA4rqi9oDhHc67@6c48a","e63ydYhNpA4rqi9oDhHc67@f9941","e9k4GpMbFEz71hEnlW9EG/@6c48a","e9k4GpMbFEz71hEnlW9EG/@f9941","f80KUJRIBIOLDKiyPGqX0D@6c48a","f80KUJRIBIOLDKiyPGqX0D@f9941","fepexl1EBJjq0Zbvi5flCD@6c48a","fepexl1EBJjq0Zbvi5flCD@f9941","ffQyL3aTBHl4xxgNKK1VAO"],"paths":{"27":["db:/internal/default_renderpipeline/builtin-forward",0]},"scenes":{"db://assets/Scene/GameScene.scene":6},"packs":{"0abd670aa":["37","33","49","39","41","45","35","54","52","43","56","59","61","63","65"],"0d0a955ce":["2","0","8","3","4","7","1","16","15","5","17","24","25","26","28"],"0f2e19270":["29","34","36","38","40","42","44","6","46","47","48","50","51","9","10","11","12","13","14","53","55","57","58","18","19","20","21","22","23","60","62","64","66","67"]},"versions":{"import":[30,"bd53b",31,"a23c5",32,"b4c59",27,"731f4"],"native":[0,"8892d",1,"90cf4",2,"64971",3,"ac0d9",4,"83fcc",5,"6d3cf",7,"0e532",8,"a0c3e",9,"d3b54",10,"b1959",11,"609c0",12,"7c9ad",13,"161af",14,"e576c",15,"5e90c",16,"c06a9",17,"7623c",18,"650fc",19,"879c3",20,"3a214",21,"5fb29",22,"da2f8",23,"1f1c5",24,"dd39b",25,"b12ee",26,"bd2c9",28,"1ebbe"]},"redirect":[],"debug":false,"extensionMap":{},"types":["cc.RenderPipeline"]}